native_rpc/__init__.py
native_rpc/deserializer.py
native_rpc/exceptions.py
native_rpc/namespace.py
native_rpc/obj_pool.py
native_rpc/serializer.py
native_rpc/server.py
native_rpc/stream.py
native_rpc_client/__init__.py
native_rpc_client/client.py
native_rpc_client/compressor.py
native_rpc_client/deserializer.py
native_rpc_client/serializer.py
native_rpc-0.1.3.dist-info/LICENSE
native_rpc-0.1.3.dist-info/METADATA
native_rpc-0.1.3.dist-info/WHEEL
native_rpc-0.1.3.dist-info/top_level.txt
native_rpc-0.1.3.dist-info/RECORD
