Metadata-Version: 2.1
Name: native-rpc
Version: 0.1.3
Summary: Native RPC framework for Python.
Home-page: https://github.com/HowyoungZhou/native-rpc
Author: Howyoung Zhou
Author-email: howyoungzhou@yahoo.com
License: UNKNOWN
Platform: UNKNOWN
Classifier: Programming Language :: Python :: 3
Classifier: License :: OSI Approved :: MIT License
Classifier: Operating System :: OS Independent
Requires-Python: >=3.6
License-File: LICENSE
Requires-Dist: aiohttp
Requires-Dist: requests
